embed_cost/__init__.py
embed_cost/cli.py
embed_cost/estimator.py
embedding_cost_estimator-1.0.1.dist-info/LICENSE
embedding_cost_estimator-1.0.1.dist-info/METADATA
embedding_cost_estimator-1.0.1.dist-info/WHEEL
embedding_cost_estimator-1.0.1.dist-info/entry_points.txt
embedding_cost_estimator-1.0.1.dist-info/RECORD
