Metadata-Version: 2.3
Name: embedding-cost-estimator
Version: 1.0.1
Summary: A lightweight Python library and CLI to estimate OpenAI embedding costs.
License: MIT
Keywords: openai,embed,embeddings,tiktoken,cost,estimation,cli
Author: Pragasen Naicker
Author-email: pnaicker.dev@gmail.com
Requires-Python: >=3.10, <4.0
Classifier: Development Status :: 5 - Production/Stable
Classifier: Intended Audience :: Developers
Classifier: License :: OSI Approved :: MIT License
Classifier: Topic :: Software Development :: Libraries :: Python Modules
Classifier: Programming Language :: Python :: 3
Classifier: Programming Language :: Python :: 3.10
Classifier: Programming Language :: Python :: 3.11
Classifier: Programming Language :: Python :: 3.12
Requires-Dist: click (>=8.1.7,<9.0.0)
Requires-Dist: tiktoken (>=0.9.0)
Project-URL: Documentation, https://github.com/pragasennaicker/embedding-cost-calc#readme
Project-URL: Homepage, https://github.com/pragasennaicker/embedding-cost-calc
Project-URL: Repository, https://github.com/pragasennaicker/embedding-cost-calc.git
